{
    "swagger": "2.0",
    "info": {
        "description": "This is a simple key-value store that allows you to store any JSON-serializable data under a key.",
        "title": "Dankey API",
        "contact": {},
        "license": {
            "name": "MIT",
            "url": "http://opensource.org/licenses/MIT"
        },
        "version": "1.0"
    },
    "paths": {
        "/decrement": {
            "post": {
                "description": "Decrement the value of a key by 1. If they value is not an integer, an error will be returned.",
                "consumes": [
                    "application/json"
                ],
                "produces": [
                    "application/json"
                ],
                "summary": "Decrement a key-value pair",
                "operationId": "decrement",
                "parameters": [
                    {
                        "description": "DecrementRequestDTO",
                        "name": "request",
                        "in": "body",
                        "required": true,
                        "schema": {
                            "$ref": "#/definitions/DTO.DecrementRequestDTO"
                        }
                    }
                ],
                "responses": {
                    "200": {
                        "description": "OK",
                        "schema": {
                            "$ref": "#/definitions/DTO.DecrementResponseDTO"
                        }
                    }
                }
            }
        },
        "/delete": {
            "delete": {
                "description": "Delete a key-value pair",
                "consumes": [
                    "application/json"
                ],
                "produces": [
                    "application/json"
                ],
                "summary": "Delete a key-value pair",
                "operationId": "delete",
                "parameters": [
                    {
                        "description": "DeleteRequestDTO",
                        "name": "request",
                        "in": "body",
                        "required": true,
                        "schema": {
                            "$ref": "#/definitions/DTO.DeleteRequestDTO"
                        }
                    }
                ],
                "responses": {
                    "200": {
                        "description": "OK",
                        "schema": {
                            "$ref": "#/definitions/DTO.DeleteResponseDTO"
                        }
                    }
                }
            }
        },
        "/get": {
            "get": {
                "description": "Retrieve the JSON Object stored under a key",
                "consumes": [
                    "application/json"
                ],
                "produces": [
                    "application/json"
                ],
                "summary": "Get a key-value pair",
                "operationId": "get",
                "parameters": [
                    {
                        "description": "GetRequestDTO",
                        "name": "request",
                        "in": "body",
                        "required": true,
                        "schema": {
                            "$ref": "#/definitions/DTO.GetRequestDTO"
                        }
                    }
                ],
                "responses": {
                    "200": {
                        "description": "OK",
                        "schema": {
                            "$ref": "#/definitions/DTO.GetResponseDTO"
                        }
                    }
                }
            }
        },
        "/increment": {
            "post": {
                "description": "Increment the value of a key by 1. If they value is not an integer, an error will be returned.",
                "consumes": [
                    "application/json"
                ],
                "produces": [
                    "application/json"
                ],
                "summary": "Increment a key-value pair",
                "operationId": "increment",
                "parameters": [
                    {
                        "description": "IncrementRequestDTO",
                        "name": "request",
                        "in": "body",
                        "required": true,
                        "schema": {
                            "$ref": "#/definitions/DTO.IncrementRequestDTO"
                        }
                    }
                ],
                "responses": {
                    "200": {
                        "description": "OK",
                        "schema": {
                            "$ref": "#/definitions/DTO.IncrementResponseDTO"
                        }
                    }
                }
            }
        },
        "/put": {
            "put": {
                "description": "Put any JSON-serializable data under a key",
                "consumes": [
                    "application/json"
                ],
                "produces": [
                    "application/json"
                ],
                "summary": "Put a key-value pair",
                "operationId": "put",
                "parameters": [
                    {
                        "description": "PutRequestDTO",
                        "name": "request",
                        "in": "body",
                        "required": true,
                        "schema": {
                            "$ref": "#/definitions/DTO.PutRequestDTO"
                        }
                    }
                ],
                "responses": {
                    "200": {
                        "description": "OK",
                        "schema": {
                            "$ref": "#/definitions/DTO.PutResponseDTO"
                        }
                    },
                    "401": {
                        "description": "Unauthorized",
                        "schema": {
                            "$ref": "#/definitions/DTO.ResponseDTO"
                        }
                    }
                }
            }
        },
        "/retrieveFromFile": {
            "post": {
                "description": "Retrieve the state of the database from a file",
                "consumes": [
                    "application/json"
                ],
                "produces": [
                    "application/json"
                ],
                "summary": "Retrieve from file",
                "operationId": "retrieveFromFile",
                "parameters": [
                    {
                        "description": "RetrieveFromFileRequestDTO",
                        "name": "request",
                        "in": "body",
                        "required": true,
                        "schema": {
                            "$ref": "#/definitions/DTO.RetrieveFromFileRequestDTO"
                        }
                    }
                ],
                "responses": {
                    "200": {
                        "description": "OK",
                        "schema": {
                            "$ref": "#/definitions/DTO.RetrieveFromFileResponseDTO"
                        }
                    }
                }
            }
        },
        "/saveToFile": {
            "post": {
                "description": "Save the current state of the database to a file",
                "consumes": [
                    "application/json"
                ],
                "produces": [
                    "application/json"
                ],
                "summary": "Save to file",
                "operationId": "saveToFile",
                "parameters": [
                    {
                        "description": "SaveToFileRequestDTO",
                        "name": "request",
                        "in": "body",
                        "required": true,
                        "schema": {
                            "$ref": "#/definitions/DTO.SaveToFileRequestDTO"
                        }
                    }
                ],
                "responses": {
                    "200": {
                        "description": "OK",
                        "schema": {
                            "$ref": "#/definitions/DTO.SaveToFileResponseDTO"
                        }
                    }
                }
            }
        }
    },
    "definitions": {
        "DTO.DecrementRequestDTO": {
            "type": "object",
            "properties": {
                "database": {
                    "type": "integer"
                },
                "key": {
                    "type": "string"
                }
            }
        },
        "DTO.DecrementResponseDTO": {
            "type": "object",
            "properties": {
                "message": {
                    "type": "string"
                },
                "success": {
                    "type": "boolean"
                },
                "value": {
                    "type": "integer"
                }
            }
        },
        "DTO.DeleteRequestDTO": {
            "type": "object",
            "properties": {
                "database": {
                    "type": "integer"
                },
                "key": {
                    "type": "string"
                }
            }
        },
        "DTO.DeleteResponseDTO": {
            "type": "object",
            "properties": {
                "message": {
                    "type": "string"
                },
                "success": {
                    "type": "boolean"
                }
            }
        },
        "DTO.GetRequestDTO": {
            "type": "object",
            "required": [
                "database",
                "key"
            ],
            "properties": {
                "database": {
                    "type": "integer"
                },
                "key": {
                    "type": "string"
                }
            }
        },
        "DTO.GetResponseDTO": {
            "type": "object",
            "properties": {
                "message": {
                    "type": "string"
                },
                "success": {
                    "type": "boolean"
                },
                "value": {}
            }
        },
        "DTO.IncrementRequestDTO": {
            "type": "object",
            "properties": {
                "database": {
                    "type": "integer"
                },
                "key": {
                    "type": "string"
                }
            }
        },
        "DTO.IncrementResponseDTO": {
            "type": "object",
            "properties": {
                "message": {
                    "type": "string"
                },
                "success": {
                    "type": "boolean"
                },
                "value": {
                    "type": "integer"
                }
            }
        },
        "DTO.PutRequestDTO": {
            "type": "object",
            "required": [
                "database",
                "key",
                "value"
            ],
            "properties": {
                "database": {
                    "type": "integer"
                },
                "key": {
                    "type": "string"
                },
                "value": {}
            }
        },
        "DTO.PutResponseDTO": {
            "type": "object",
            "properties": {
                "message": {
                    "type": "string"
                },
                "success": {
                    "type": "boolean"
                }
            }
        },
        "DTO.ResponseDTO": {
            "type": "object",
            "properties": {
                "message": {
                    "type": "string"
                },
                "success": {
                    "type": "boolean"
                }
            }
        },
        "DTO.RetrieveFromFileRequestDTO": {
            "type": "object",
            "properties": {
                "filePath": {
                    "type": "string"
                }
            }
        },
        "DTO.RetrieveFromFileResponseDTO": {
            "type": "object",
            "properties": {
                "filePath": {
                    "type": "string"
                },
                "message": {
                    "type": "string"
                },
                "size": {
                    "type": "integer"
                },
                "sizeHumanReadable": {
                    "type": "string"
                },
                "success": {
                    "type": "boolean"
                }
            }
        },
        "DTO.SaveToFileRequestDTO": {
            "type": "object",
            "properties": {
                "filePath": {
                    "type": "string"
                }
            }
        },
        "DTO.SaveToFileResponseDTO": {
            "type": "object",
            "properties": {
                "filePath": {
                    "type": "string"
                },
                "message": {
                    "type": "string"
                },
                "size": {
                    "type": "integer"
                },
                "sizeHumanReadable": {
                    "type": "string"
                },
                "success": {
                    "type": "boolean"
                }
            }
        }
    },
    "securityDefinitions": {
        "BasicAuth": {
            "type": "basic"
        }
    }
}